zimagi/__init__.py
zimagi/auth.py
zimagi/client.py
zimagi/codecs.py
zimagi/collection.py
zimagi/datetime.py
zimagi/encryption.py
zimagi/exceptions.py
zimagi/parallel.py
zimagi/settings.py
zimagi/transports.py
zimagi/utility.py
zimagi/command/__init__.py
zimagi/command/client.py
zimagi/command/codecs.py
zimagi/command/messages.py
zimagi/command/response.py
zimagi/command/schema.py
zimagi/command/transports.py
zimagi/data/__init__.py
zimagi/data/client.py
zimagi/data/codecs.py
zimagi/data/transports.py
zimagi-0.14.22.data/scripts/zimagi
zimagi-0.14.22.dist-info/METADATA
zimagi-0.14.22.dist-info/WHEEL
zimagi-0.14.22.dist-info/top_level.txt
zimagi-0.14.22.dist-info/RECORD
