Metadata-Version: 2.4
Name: zimagi
Version: 0.14.22
Summary: Zimagi CLI and API Client
Home-page: https://github.com/zimagi/zimagi
Author: Adrian Webb
Author-email: adrian.webb@dccs.tech
License: Apache 2.0
Classifier: Programming Language :: Python :: 3
Classifier: License :: OSI Approved :: Apache Software License
Classifier: Operating System :: OS Independent
Requires-Dist: requests==2.32.*
Requires-Dist: pycryptodome==3.23.*
Requires-Dist: terminaltables==3.1.*
Requires-Dist: numpy==2.3.*
Requires-Dist: pandas==2.3.*
Requires-Dist: tblib==3.1.*
Requires-Dist: validators==0.35.*
Requires-Dist: python-magic==0.4.*
Dynamic: author
Dynamic: author-email
Dynamic: classifier
Dynamic: description-content-type
Dynamic: home-page
Dynamic: license
Dynamic: requires-dist
Dynamic: summary
